jupyter_ra_extension/__init__.py
jupyter_ra_extension/_version.py
jupyter_ra_extension-1.4.201.data/data/share/jupyter/labextensions/jupyter-ra-extension/package.json
jupyter_ra_extension-1.4.201.data/data/share/jupyter/labextensions/jupyter-ra-extension/schemas/jupyter-ra-extension/package.json.orig
jupyter_ra_extension-1.4.201.data/data/share/jupyter/labextensions/jupyter-ra-extension/schemas/jupyter-ra-extension/plugin.json
jupyter_ra_extension-1.4.201.data/data/share/jupyter/labextensions/jupyter-ra-extension/static/277.a152fe877726421b0951.js
jupyter_ra_extension-1.4.201.data/data/share/jupyter/labextensions/jupyter-ra-extension/static/44.5d69de4d0a5a5f1e3fa7.js
jupyter_ra_extension-1.4.201.data/data/share/jupyter/labextensions/jupyter-ra-extension/static/728.21199263c3af514a5f7b.js
jupyter_ra_extension-1.4.201.data/data/share/jupyter/labextensions/jupyter-ra-extension/static/remoteEntry.4f5edcc29988c1792805.js
jupyter_ra_extension-1.4.201.data/data/share/jupyter/labextensions/jupyter-ra-extension/static/style.js
jupyter_ra_extension-1.4.201.data/data/share/jupyter/labextensions/jupyter-ra-extension/static/third-party-licenses.json
jupyter_ra_extension-1.4.201.data/data/share/jupyter/labextensions/jupyter-ra-extension/install.json
jupyter_ra_extension-1.4.201.dist-info/METADATA
jupyter_ra_extension-1.4.201.dist-info/WHEEL
jupyter_ra_extension-1.4.201.dist-info/licenses/LICENSE
jupyter_ra_extension-1.4.201.dist-info/RECORD
