Metadata-Version: 2.4
Name: jupyter_ra_extension
Version: 1.4.201
Summary: Relational Algebra Symbols in Jupyter Lab
Project-URL: Homepage, https://dbgit.prakinf.tu-ilmenau.de/ertr8623/jupyter-duckdb
Project-URL: Bug Tracker, https://dbgit.prakinf.tu-ilmenau.de/ertr8623/jupyter-duckdb/issues
Project-URL: Repository, https://dbgit.prakinf.tu-ilmenau.de/ertr8623/jupyter-duckdb.git
Author-email: Eric Tröbs <Eric.Troebs@tu-ilmenau.de>
License: BSD 3-Clause License
License-File: LICENSE
Keywords: jupyter,jupyterlab,jupyterlab-extension
Classifier: Framework :: Jupyter
Classifier: Framework :: Jupyter :: JupyterLab
Classifier: Framework :: Jupyter :: JupyterLab :: 4
Classifier: Framework :: Jupyter :: JupyterLab :: Extensions
Classifier: Framework :: Jupyter :: JupyterLab :: Extensions :: Prebuilt
Classifier: License :: OSI Approved :: BSD License
Classifier: Programming Language :: Python
Classifier: Programming Language :: Python :: 3
Classifier: Programming Language :: Python :: 3.9
Classifier: Programming Language :: Python :: 3.10
Classifier: Programming Language :: Python :: 3.11
Classifier: Programming Language :: Python :: 3.12
Classifier: Programming Language :: Python :: 3.13
Requires-Python: >=3.9
